nanosurf/__init__.py
nanosurf/_version.py
nanosurf/hook-nanosurf.py
nanosurf/app/app_DriveAFM_Tip_Access_Addon/gui.py
nanosurf/app/app_DriveAFM_Tip_Access_Addon/main.py
nanosurf/app/app_DriveAFM_Tip_Access_Addon/settings.py
nanosurf/app/app_DriveAFM_Tip_Access_Addon/worker.py
nanosurf/app/app_DriveAFM_Tip_Access_Addon/.vscode/launch.json
nanosurf/app/app_DriveAFM_Tip_Access_Addon/__pycache__/device_stm_addon.cpython-310.pyc
nanosurf/app/app_DriveAFM_Tip_Access_Addon/__pycache__/device_stm_addon.cpython-39.pyc
nanosurf/app/app_DriveAFM_Tip_Access_Addon/__pycache__/device_tip_access_addon.cpython-39.pyc
nanosurf/app/app_DriveAFM_Tip_Access_Addon/__pycache__/device_tip_current_addon.cpython-39.pyc
nanosurf/app/app_DriveAFM_Tip_Access_Addon/__pycache__/gui.cpython-310.pyc
nanosurf/app/app_DriveAFM_Tip_Access_Addon/__pycache__/gui.cpython-313.pyc
nanosurf/app/app_DriveAFM_Tip_Access_Addon/__pycache__/gui.cpython-39.pyc
nanosurf/app/app_DriveAFM_Tip_Access_Addon/__pycache__/settings.cpython-310.pyc
nanosurf/app/app_DriveAFM_Tip_Access_Addon/__pycache__/settings.cpython-313.pyc
nanosurf/app/app_DriveAFM_Tip_Access_Addon/__pycache__/settings.cpython-39.pyc
nanosurf/app/app_DriveAFM_Tip_Access_Addon/__pycache__/worker.cpython-310.pyc
nanosurf/app/app_DriveAFM_Tip_Access_Addon/__pycache__/worker.cpython-313.pyc
nanosurf/app/app_DriveAFM_Tip_Access_Addon/__pycache__/worker.cpython-39.pyc
nanosurf/app/app_DriveAFM_Tip_Access_Addon/__pycache__/worker_task.cpython-310.pyc
nanosurf/app/app_DriveAFM_Tip_Current_Addon/gui.py
nanosurf/app/app_DriveAFM_Tip_Current_Addon/main.py
nanosurf/app/app_DriveAFM_Tip_Current_Addon/settings.py
nanosurf/app/app_DriveAFM_Tip_Current_Addon/worker.py
nanosurf/app/app_DriveAFM_Tip_Current_Addon/.vscode/launch.json
nanosurf/app/app_DriveAFM_Tip_Current_Addon/__pycache__/device_stm_addon.cpython-310.pyc
nanosurf/app/app_DriveAFM_Tip_Current_Addon/__pycache__/device_stm_addon.cpython-39.pyc
nanosurf-1.13.4.dist-info/licenses/LICENSE
nanosurf-1.13.4.dist-info/METADATA
nanosurf-1.13.4.dist-info/WHEEL
nanosurf-1.13.4.dist-info/entry_points.txt
nanosurf-1.13.4.dist-info/top_level.txt
nanosurf-1.13.4.dist-info/RECORD
