Metadata-Version: 2.4
Name: nanosurf
Version: 1.13.4
Summary: Python API for Nanosurf controllers and Nanosurf style application framework
Author: Nanosurf AG
Author-email: scripting@nanosurf.com
License: MIT
Classifier: Programming Language :: Python :: 3.10
Classifier: Programming Language :: Python :: 3.11
Classifier: Programming Language :: Python :: 3.12
Classifier: Programming Language :: Python :: 3.13
Classifier: Programming Language :: Python :: 3.14
Classifier: License :: OSI Approved :: MIT License
Requires-Python: >=3.10, <3.15
License-File: LICENSE
Requires-Dist: numpy
Requires-Dist: scipy
Requires-Dist: h5py>=3.11
Requires-Dist: psutil
Requires-Dist: debugpy
Requires-Dist: pywin32>=311; platform_system == "Windows"
Requires-Dist: lupa>=2.6; platform_system == "Windows"
Requires-Dist: smbus3; platform_system == "Linux"
Requires-Dist: matplotlib
Requires-Dist: notebook
Requires-Dist: pyside6>=6.10
Requires-Dist: pyqtgraph>=0.14
Dynamic: author
Dynamic: author-email
Dynamic: classifier
Dynamic: description
Dynamic: description-content-type
Dynamic: license
Dynamic: license-file
Dynamic: requires-dist
Dynamic: requires-python
Dynamic: summary
